Metadata-Version: 2.4
Name: llama-index-multi-modal-llms-mistralai
Version: 0.5.1
Summary: llama-index multi-modal-llms mistral integration
Author-email: Your Name <you@example.com>
License-Expression: MIT
License-File: LICENSE
Requires-Python: <4.0,>=3.9
Requires-Dist: llama-index-core<0.15,>=0.13.0
Requires-Dist: llama-index-llms-mistralai<0.8,>=0.7.0
